src/__init__.py
src/api_requests.py
src/glade_constants.py
src/glade_functions.py
src/helpers.py
glade_api_python-1.0.0.dist-info/LICENSE
glade_api_python-1.0.0.dist-info/METADATA
glade_api_python-1.0.0.dist-info/WHEEL
glade_api_python-1.0.0.dist-info/top_level.txt
glade_api_python-1.0.0.dist-info/RECORD
