Metadata-Version: 2.1
Name: glade-api-python
Version: 1.0.0
Summary: Glade API Python Package
Author: Oluwatobi Adelabu
Author-email: Oluwatobi <Oluwatobi@glade.ng>
Project-URL: Homepage, https://gitlab.com/gladepay-apis/gladepython
Project-URL: Issues, https://gitlab.com/gladepay-apis/gladepython/issues
Project-URL: Documentation, https://developer.gladefinance.co/docs
Classifier: Programming Language :: Python :: 3
Classifier: License :: OSI Approved :: MIT License
Classifier: Operating System :: OS Independent
Requires-Python: >=3.8
License-File: LICENSE
